LICENSE
MANIFEST.in
README.rst
setup.py
asianet_tracker.egg-info/PKG-INFO
asianet_tracker.egg-info/SOURCES.txt
asianet_tracker.egg-info/dependency_links.txt
asianet_tracker.egg-info/top_level.txt
tracker/__init__.py
tracker/admin.py
tracker/models.py
tracker/tests.py
tracker/views.py
tracker/migrations/0001_initial.py
tracker/migrations/__init__.py