Metadata-Version: 1.1
Name: asianet-tracker
Version: 0.4
Summary: A simple Django app to track data from URL visits
Home-page: https://www.example.com/
Author: Sachin Prabhu
Author-email: sachin.prabhu@kuliza.com
License: BSD License
Platform: UNKNOWN
Classifier: Environment :: Web Environment
Classifier: Framework :: Django
Classifier: Framework :: Django :: 1.8
Classifier: Intended Audience :: Developers
Classifier: License :: OSI Approved :: BSD License
Classifier: Operating System :: OS Independent
Classifier: Programming Language :: Python
Classifier: Programming Language :: Python :: 2
Classifier: Topic :: Internet :: WWW/HTTP
Classifier: Topic :: Internet :: WWW/HTTP :: Dynamic Content
